whillpy/__init__.py
whillpy/options.py
whillpy/whill.py
whillpy-0.2.dist-info/LICENSE
whillpy-0.2.dist-info/METADATA
whillpy-0.2.dist-info/WHEEL
whillpy-0.2.dist-info/top_level.txt
whillpy-0.2.dist-info/RECORD
