Metadata-Version: 2.1
Name: whillpy
Version: 0.2
Summary: Unofficial python package for WHILL Model CK control
Home-page: http://github.com/ShibataLab/whillpy
Author: Ravi Prakash Joshi
Author-email: joshi.ravi-prakash869@mail.kyutech.jp
License: MIT
Platform: UNKNOWN
Classifier: Programming Language :: Python
Classifier: License :: OSI Approved :: MIT License
Classifier: Operating System :: OS Independent
Requires-Dist: pyserial
